azmailer/__init__.py
azmailer/_routing.py
azmailer/_version.py
azmailer/azmailer.py
azmailer/utils/__init__.py
azmailer-1.0.1.dist-info/LICENSE
azmailer-1.0.1.dist-info/METADATA
azmailer-1.0.1.dist-info/WHEEL
azmailer-1.0.1.dist-info/top_level.txt
azmailer-1.0.1.dist-info/RECORD
