Metadata-Version: 2.1
Name: azmailer
Version: 1.0.1
Summary: send mails from az
Author: anglisanosa
Author-email: marcanglisano@gmail.com
Project-URL: Documentation, https://anglisanosa.github.io/azmailer/
Project-URL: Bug Reports, https://github.com/anglisanosa/azmailer/issues
Project-URL: Source, https://github.com/anglisanosa/azmailer
Classifier: Programming Language :: Python :: 3
Classifier: Operating System :: OS Independent
Requires-Python: >=3.8
License-File: LICENSE
Requires-Dist: azure-communication-email ==1.0.*
Requires-Dist: pathutility ==1.0.*
